Verilog/Dff/dfftb.v
//Tester module sends a periodic clock signal to the flip-flop
module tester(q,qn,clk,d);
	input q,qn;
	output clk,d;
	reg clk,d;

	//Run the test once
	initial
	begin
		clk=0;
		//Dump results of the simulation to ff.cvd
		$dumpfile("dff.vcd");
		$dumpvars;
		//Generate input signal d
		   d=0; #9 d=1; #1 d=0; #1 d=1; #2 d=0; #1 d=1; #12 d=0;
		#1 d=1; #2 d=0; #1 d=1; #1 d=0; #1 d=1; #1 d=0; # 7 d=1;
		#8 $finish;
	end

	//Generate periodic clock signal
	always
	begin
		#5 clk=!clk;
	end
endmodule

Verilog/Dff/sim/dff.vcd
$date
	Sun Dec 18 14:55:44 2016
$end
$version
	Icarus Verilog
$end
$timescale
	1s
$end
$scope module tester $end
$var wire 1 ! q $end
$var wire 1 " qn $end
$var reg 1 # clk $end
$var reg 1 $ d $end
$upscope $end
$enddefinitions $end
#0
$dumpvars
0$
0#
z"
z!
$end
#5
1#
#9
1$
#10
0$
0#
#11
1$
#13
0$
#14
1$
#15
1#
#20
0#
#25
1#
#26
0$
#27
1$
#29
0$
#30
1$
0#
#31
0$
#32
1$
#33
0$
#35
1#
#40
0#
1$
