Verilog/first_counter.V








             //-----------------------------------------------------
   // This is my second Verilog Design
   // Design Name : first_counter
   // File Name : first_counter.v
   // Function : This is a 4 bit up-counter with
   // Synchronous active high reset and
   // with active high enable signal
   //-----------------------------------------------------
   module first_counter (
  clock , // Clock input of the design
  reset , // active high, synchronous Reset input
  enable , // Active high enable signal for counter
  counter_out // 4 bit vector output of the counter
  ); // End of port list
  //-------------Input Ports-----------------------------
  input clock ;
  input reset ;
  input enable ;
  //-------------Output Ports----------------------------
  output [3:0] counter_out ;
  //-------------Input ports Data Type-------------------
  // By rule all the input ports should be wires
  wire clock ;
  wire reset ;
  wire enable ;
  //-------------Output Ports Data Type------------------
  // Output port can be a storage element (reg) or a wire
  reg [3:0] counter_out ;

  //------------Code Starts Here-------------------------
  // Since this counter is a positive edge trigged one,
  // We trigger the below block with respect to positive
  // edge of the clock.
  always @ (posedge clock)
  begin : COUNTER // Block Name
    // At every rising edge of clock we check if reset is active
    // If active, we load the counter output with 4'b0000
    if (reset == 1'b1) begin
      counter_out <=  #1  4'b0000;
    end
    // If enable is active, then we increment the counter
    else if (enable == 1'b1) begin
      counter_out <=  #1  counter_out + 1;
    end
  end // End of Block COUNTER
endmodule

Verilog/Verilog1.V
`include "first_counter.v"
module first_counter_tb();
// Declare inputs as regs and outputs as wires
reg clock, reset, enable;
wire [3:0] counter_out;

// Initialize all variables
initial begin
  $display ("time\t clk reset enable counter");
  $monitor ("%g\t %b   %b     %b      %b",
      $time, clock, reset, enable, counter_out);
  clock = 1;       // initial value of clock
  reset = 0;       // initial value of reset
  enable = 0;      // initial value of enable
  #5 reset = 1;    // Assert the reset
  #10 reset = 0;   // De-assert the reset
  #10 enable = 1;  // Assert enable
  #100 enable = 0; // De-assert enable
  #5 $finish;      // Terminate simulation
end

// Clock generator
always begin
  #5 clock = ~clock; // Toggle clock every 5 ticks
end

// Connect DUT to test bench
first_counter U_counter (
clock,
reset,
enable,
counter_out
);

endmodule

Verilog/Verilog/dff.vcd
$date
	Sun Dec 18 14:58:04 2016
$end
$version
	Icarus Verilog
$end
$timescale
	1s
$end
$scope module first_counter_tb $end
$var wire 4 ! counter_out [3:0] $end
$var reg 1 " clock $end
$var reg 1 # enable $end
$var reg 1 $ reset $end
$scope module U_counter $end
$var wire 1 " clock $end
$var wire 1 # enable $end
$var wire 1 $ reset $end
$var reg 4 % counter_out [3:0] $end
$scope begin COUNTER $end
$upscope $end
$upscope $end
$upscope $end
$enddefinitions $end
#0
$dumpvars
bx %
0$
0#
1"
bx !
$end
#5
0"
1$
#10
1"
#11
b0 !
b0 %
#15
0"
0$
#20
1"
#25
0"
1#
#30
1"
#31
b1 !
b1 %
#35
0"
#40
1"
#41
b10 !
b10 %
#45
0"
#50
1"
#51
b11 !
b11 %
#55
0"
#60
1"
#61
b100 !
b100 %
#65
0"
#70
1"
#71
b101 !
b101 %
#75
0"
#80
1"
#81
b110 !
b110 %
#85
0"
#90
1"
#91
b111 !
b111 %
#95
0"
#100
1"
#101
b1000 !
b1000 %
#105
0"
#110
1"
#111
b1001 !
b1001 %
#115
0"
#120
1"
#121
b1010 !
b1010 %
#125
0"
0#
