Verilog/Verilog/first_counter.V

             //-----------------------------------------------------
   // This is my second Verilog Design
   // Design Name : first_counter
   // File Name : first_counter.v
   // Function : This is a 4 bit up-counter with
   // Synchronous active high reset and
   // with active high enable signal
   //-----------------------------------------------------
   module first_counter (
  clock , // Clock input of the design
  reset , // active high, synchronous Reset input
  enable , // Active high enable signal for counter
  counter_out,// 4 bit vector output of the counter
  clock_out

  ); // End of port list
  //-------------Input Ports-----------------------------
  input clock ;
  input reset ;
  input enable ;
  //-------------Output Ports----------------------------
  output [3:0] counter_out ;
  output clock_out;
  
  //-------------Input ports Data Type-------------------
  // By rule all the input ports should be wires
  wire clock ;
  wire reset ;
  wire enable ;
  //-------------Output Ports Data Type------------------
  // Output port can be a storage element (reg) or a wire
  reg [3:0] counter_out ;
  reg clock_out;
  //------------Code Starts Here-------------------------
  // Since this counter is a positive edge trigged one,
  // We trigger the below block with respect to positive
  // edge of the clock.
  always @ (posedge reset)
  begin
      counter_out <=  #1  4'b0000;
	  clock_out <= 1'b0;
  end
  
  always @ (posedge clock)
  begin : COUNTER // Block Name
    // At every rising edge of clock we check if reset is active
    // If enable is active, then we increment the counter
    if (enable == 1'b1) begin
  	 if(counter_out==4'b1111) begin
	  clock_out <= #1 1'b1;
	 end
	 else
	 begin
	  clock_out <= #1 1'b0;
	 end
	 counter_out <=  #1 counter_out + 1;
	 
    end
  end // End of Block COUNTER
endmodule

Verilog/Verilog/Verilog1.V
`include "first_counter.v"
module first_counter_tb();
// Declare inputs as regs and outputs as wires
reg clock, reset, enable;
wire carry_out;
wire carry_out1;

wire [3:0] counter_out;
wire [3:0] counter_out1;

// Initialize all variables
initial begin
		$dumpfile("dump.vcd");
		$dumpvars;
  $display ("time\t clk reset enable counter");
  /*$monitor ("%g\t %b   %b     %b      %b",
      $time, clock, reset, enable, counter_out);*/
  clock = 1;       // initial value of clock
  reset = 0;       // initial value of reset
  enable = 0;      // initial value of enable
  #5 reset = 1;    // Assert the reset
  #10 reset = 0;   // De-assert the reset
  #10 enable = 1;  // Assert enable
  #4500 enable = 0; // De-assert enable
  #5 $finish;      // Terminate simulation
end

// Clock generator
always begin
  #5 clock = ~clock; // Toggle clock every 5 ticks
end

// Connect DUT to test bench
first_counter My_counter (
clock,
reset,
enable,
counter_out,
carry_out
);

first_counter U_counter (
carry_out,
reset,
enable,
counter_out1,
carry_out1
);

endmodule

Verilog/Verilog/sim/Veri1.vcd
$date
	Mon Dec 19 14:55:18 2016
$end
$version
	Icarus Verilog
$end
$timescale
	1s
$end
$scope module first_counter_tb $end
$var wire 4 ! counter_out1 [3:0] $end
$var wire 4 " counter_out [3:0] $end
$var wire 1 # carry_out1 $end
$var wire 1 $ carry_out $end
$var reg 1 % clock $end
$var reg 1 & enable $end
$var reg 1 ' reset $end
$scope module My_counter $end
$var wire 1 % clock $end
$var wire 1 & enable $end
$var wire 1 ' reset $end
$var reg 1 $ clock_out $end
$var reg 4 ( counter_out [3:0] $end
$scope begin COUNTER $end
$upscope $end
$upscope $end
$scope module U_counter $end
$var wire 1 $ clock $end
$var wire 1 & enable $end
$var wire 1 ' reset $end
$var reg 1 # clock_out $end
$var reg 4 ) counter_out [3:0] $end
$scope begin COUNTER $end
$upscope $end
$upscope $end
$upscope $end
$enddefinitions $end
#0
$dumpvars
bx )
bx (
0'
0&
1%
x$
x#
bx "
bx !
$end
#5
0$
0#
0%
1'
#6
b0 "
b0 (
b0 !
b0 )
#10
1%
#15
0%
0'
#20
1%
#25
0%
1&
#30
1%
#31
b1 "
b1 (
#35
0%
#40
1%
#41
b10 "
b10 (
#45
0%
#50
1%
#51
b11 "
b11 (
#55
0%
#60
1%
#61
b100 "
b100 (
#65
0%
#70
1%
#71
b101 "
b101 (
#75
0%
#80
1%
#81
b110 "
b110 (
#85
0%
#90
1%
#91
b111 "
b111 (
#95
0%
#100
1%
#101
b1000 "
b1000 (
#105
0%
#110
1%
#111
b1001 "
b1001 (
#115
0%
#120
1%
#121
b1010 "
b1010 (
#125
0%
#130
1%
#131
b1011 "
b1011 (
#135
0%
#140
1%
#141
b1100 "
b1100 (
#145
0%
#150
1%
#151
b1101 "
b1101 (
#155
0%
#160
1%
#161
b1110 "
b1110 (
#165
0%
#170
1%
#171
b1111 "
b1111 (
#175
0%
#180
1%
#181
b0 "
b0 (
1$
#182
b1 !
b1 )
#185
0%
#190
1%
#191
b1 "
b1 (
0$
#195
0%
#200
1%
#201
b10 "
b10 (
#205
0%
#210
1%
#211
b11 "
b11 (
#215
0%
#220
1%
#221
b100 "
b100 (
#225
0%
#230
1%
#231
b101 "
b101 (
#235
0%
#240
1%
#241
b110 "
b110 (
#245
0%
#250
1%
#251
b111 "
b111 (
#255
0%
#260
1%
#261
b1000 "
b1000 (
#265
0%
#270
1%
#271
b1001 "
b1001 (
#275
0%
#280
1%
#281
b1010 "
b1010 (
#285
0%
#290
1%
#291
b1011 "
b1011 (
#295
0%
#300
1%
#301
b1100 "
b1100 (
#305
0%
#310
1%
#311
b1101 "
b1101 (
#315
0%
#320
1%
#321
b1110 "
b1110 (
#325
0%
#330
1%
#331
b1111 "
b1111 (
#335
0%
#340
1%
#341
b0 "
b0 (
1$
#342
b10 !
b10 )
#345
0%
#350
1%
#351
b1 "
b1 (
0$
#355
0%
#360
1%
#361
b10 "
b10 (
#365
0%
#370
1%
#371
b11 "
b11 (
#375
0%
#380
1%
#381
b100 "
b100 (
#385
0%
#390
1%
#391
b101 "
b101 (
#395
0%
#400
1%
#401
b110 "
b110 (
#405
0%
#410
1%
#411
b111 "
b111 (
#415
0%
#420
1%
#421
b1000 "
b1000 (
#425
0%
#430
1%
#431
b1001 "
b1001 (
#435
0%
#440
1%
#441
b1010 "
b1010 (
#445
0%
#450
1%
#451
b1011 "
b1011 (
#455
0%
#460
1%
#461
b1100 "
b1100 (
#465
0%
#470
1%
#471
b1101 "
b1101 (
#475
0%
#480
1%
#481
b1110 "
b1110 (
#485
0%
#490
1%
#491
b1111 "
b1111 (
#495
0%
#500
1%
#501
b0 "
b0 (
1$
#502
b11 !
b11 )
#505
0%
#510
1%
#511
b1 "
b1 (
0$
#515
0%
#520
1%
#521
b10 "
b10 (
#525
0%
#530
1%
#531
b11 "
b11 (
#535
0%
#540
1%
#541
b100 "
b100 (
#545
0%
#550
1%
#551
b101 "
b101 (
#555
0%
#560
1%
#561
b110 "
b110 (
#565
0%
#570
1%
#571
b111 "
b111 (
#575
0%
#580
1%
#581
b1000 "
b1000 (
#585
0%
#590
1%
#591
b1001 "
b1001 (
#595
0%
#600
1%
#601
b1010 "
b1010 (
#605
0%
#610
1%
#611
b1011 "
b1011 (
#615
0%
#620
1%
#621
b1100 "
b1100 (
#625
0%
#630
1%
#631
b1101 "
b1101 (
#635
0%
#640
1%
#641
b1110 "
b1110 (
#645
0%
#650
1%
#651
b1111 "
b1111 (
#655
0%
#660
1%
#661
b0 "
b0 (
1$
#662
b100 !
b100 )
#665
0%
#670
1%
#671
b1 "
b1 (
0$
#675
0%
#680
1%
#681
b10 "
b10 (
#685
0%
#690
1%
#691
b11 "
b11 (
#695
0%
#700
1%
#701
b100 "
b100 (
#705
0%
#710
1%
#711
b101 "
b101 (
#715
0%
#720
1%
#721
b110 "
b110 (
#725
0%
#730
1%
#731
b111 "
b111 (
#735
0%
#740
1%
#741
b1000 "
b1000 (
#745
0%
#750
1%
#751
b1001 "
b1001 (
#755
0%
#760
1%
#761
b1010 "
b1010 (
#765
0%
#770
1%
#771
b1011 "
b1011 (
#775
0%
#780
1%
#781
b1100 "
b1100 (
#785
0%
#790
1%
#791
b1101 "
b1101 (
#795
0%
#800
1%
#801
b1110 "
b1110 (
#805
0%
#810
1%
#811
b1111 "
b1111 (
#815
0%
#820
1%
#821
b0 "
b0 (
1$
#822
b101 !
b101 )
#825
0%
#830
1%
#831
b1 "
b1 (
0$
#835
0%
#840
1%
#841
b10 "
b10 (
#845
0%
#850
1%
#851
b11 "
b11 (
#855
0%
#860
1%
#861
b100 "
b100 (
#865
0%
#870
1%
#871
b101 "
b101 (
#875
0%
#880
1%
#881
b110 "
b110 (
#885
0%
#890
1%
#891
b111 "
b111 (
#895
0%
#900
1%
#901
b1000 "
b1000 (
#905
0%
#910
1%
#911
b1001 "
b1001 (
#915
0%
#920
1%
#921
b1010 "
b1010 (
#925
0%
#930
1%
#931
b1011 "
b1011 (
#935
0%
#940
1%
#941
b1100 "
b1100 (
#945
0%
#950
1%
#951
b1101 "
b1101 (
#955
0%
#960
1%
#961
b1110 "
b1110 (
#965
0%
#970
1%
#971
b1111 "
b1111 (
#975
0%
#980
1%
#981
b0 "
b0 (
1$
#982
b110 !
b110 )
#985
0%
#990
1%
#991
b1 "
b1 (
0$
#995
0%
#1000
1%
#1001
b10 "
b10 (
#1005
0%
#1010
1%
#1011
b11 "
b11 (
#1015
0%
#1020
1%
#1021
b100 "
b100 (
#1025
0%
#1030
1%
#1031
b101 "
b101 (
#1035
0%
#1040
1%
#1041
b110 "
b110 (
#1045
0%
#1050
1%
#1051
b111 "
b111 (
#1055
0%
#1060
1%
#1061
b1000 "
b1000 (
#1065
0%
#1070
1%
#1071
b1001 "
b1001 (
#1075
0%
#1080
1%
#1081
b1010 "
b1010 (
#1085
0%
#1090
1%
#1091
b1011 "
b1011 (
#1095
0%
#1100
1%
#1101
b1100 "
b1100 (
#1105
0%
#1110
1%
#1111
b1101 "
b1101 (
#1115
0%
#1120
1%
#1121
b1110 "
b1110 (
#1125
0%
#1130
1%
#1131
b1111 "
b1111 (
#1135
0%
#1140
1%
#1141
b0 "
b0 (
1$
#1142
b111 !
b111 )
#1145
0%
#1150
1%
#1151
b1 "
b1 (
0$
#1155
0%
#1160
1%
#1161
b10 "
b10 (
#1165
0%
#1170
1%
#1171
b11 "
b11 (
#1175
0%
#1180
1%
#1181
b100 "
b100 (
#1185
0%
#1190
1%
#1191
b101 "
b101 (
#1195
0%
#1200
1%
#1201
b110 "
b110 (
#1205
0%
#1210
1%
#1211
b111 "
b111 (
#1215
0%
#1220
1%
#1221
b1000 "
b1000 (
#1225
0%
#1230
1%
#1231
b1001 "
b1001 (
#1235
0%
#1240
1%
#1241
b1010 "
b1010 (
#1245
0%
#1250
1%
#1251
b1011 "
b1011 (
#1255
0%
#1260
1%
#1261
b1100 "
b1100 (
#1265
0%
#1270
1%
#1271
b1101 "
b1101 (
#1275
0%
#1280
1%
#1281
b1110 "
b1110 (
#1285
0%
#1290
1%
#1291
b1111 "
b1111 (
#1295
0%
#1300
1%
#1301
b0 "
b0 (
1$
#1302
b1000 !
b1000 )
#1305
0%
#1310
1%
#1311
b1 "
b1 (
0$
#1315
0%
#1320
1%
#1321
b10 "
b10 (
#1325
0%
#1330
1%
#1331
b11 "
b11 (
#1335
0%
#1340
1%
#1341
b100 "
b100 (
#1345
0%
#1350
1%
#1351
b101 "
b101 (
#1355
0%
#1360
1%
#1361
b110 "
b110 (
#1365
0%
#1370
1%
#1371
b111 "
b111 (
#1375
0%
#1380
1%
#1381
b1000 "
b1000 (
#1385
0%
#1390
1%
#1391
b1001 "
b1001 (
#1395
0%
#1400
1%
#1401
b1010 "
b1010 (
#1405
0%
#1410
1%
#1411
b1011 "
b1011 (
#1415
0%
#1420
1%
#1421
b1100 "
b1100 (
#1425
0%
#1430
1%
#1431
b1101 "
b1101 (
#1435
0%
#1440
1%
#1441
b1110 "
b1110 (
#1445
0%
#1450
1%
#1451
b1111 "
b1111 (
#1455
0%
#1460
1%
#1461
b0 "
b0 (
1$
#1462
b1001 !
b1001 )
#1465
0%
#1470
1%
#1471
b1 "
b1 (
0$
#1475
0%
#1480
1%
#1481
b10 "
b10 (
#1485
0%
#1490
1%
#1491
b11 "
b11 (
#1495
0%
#1500
1%
#1501
b100 "
b100 (
#1505
0%
#1510
1%
#1511
b101 "
b101 (
#1515
0%
#1520
1%
#1521
b110 "
b110 (
#1525
0%
#1530
1%
#1531
b111 "
b111 (
#1535
0%
#1540
1%
#1541
b1000 "
b1000 (
#1545
0%
#1550
1%
#1551
b1001 "
b1001 (
#1555
0%
#1560
1%
#1561
b1010 "
b1010 (
#1565
0%
#1570
1%
#1571
b1011 "
b1011 (
#1575
0%
#1580
1%
#1581
b1100 "
b1100 (
#1585
0%
#1590
1%
#1591
b1101 "
b1101 (
#1595
0%
#1600
1%
#1601
b1110 "
b1110 (
#1605
0%
#1610
1%
#1611
b1111 "
b1111 (
#1615
0%
#1620
1%
#1621
b0 "
b0 (
1$
#1622
b1010 !
b1010 )
#1625
0%
#1630
1%
#1631
b1 "
b1 (
0$
#1635
0%
#1640
1%
#1641
b10 "
b10 (
#1645
0%
#1650
1%
#1651
b11 "
b11 (
#1655
0%
#1660
1%
#1661
b100 "
b100 (
#1665
0%
#1670
1%
#1671
b101 "
b101 (
#1675
0%
#1680
1%
#1681
b110 "
b110 (
#1685
0%
#1690
1%
#1691
b111 "
b111 (
#1695
0%
#1700
1%
#1701
b1000 "
b1000 (
#1705
0%
#1710
1%
#1711
b1001 "
b1001 (
#1715
0%
#1720
1%
#1721
b1010 "
b1010 (
#1725
0%
#1730
1%
#1731
b1011 "
b1011 (
#1735
0%
#1740
1%
#1741
b1100 "
b1100 (
#1745
0%
#1750
1%
#1751
b1101 "
b1101 (
#1755
0%
#1760
1%
#1761
b1110 "
b1110 (
#1765
0%
#1770
1%
#1771
b1111 "
b1111 (
#1775
0%
#1780
1%
#1781
b0 "
b0 (
1$
#1782
b1011 !
b1011 )
#1785
0%
#1790
1%
#1791
b1 "
b1 (
0$
#1795
0%
#1800
1%
#1801
b10 "
b10 (
#1805
0%
#1810
1%
#1811
b11 "
b11 (
#1815
0%
#1820
1%
#1821
b100 "
b100 (
#1825
0%
#1830
1%
#1831
b101 "
b101 (
#1835
0%
#1840
1%
#1841
b110 "
b110 (
#1845
0%
#1850
1%
#1851
b111 "
b111 (
#1855
0%
#1860
1%
#1861
b1000 "
b1000 (
#1865
0%
#1870
1%
#1871
b1001 "
b1001 (
#1875
0%
#1880
1%
#1881
b1010 "
b1010 (
#1885
0%
#1890
1%
#1891
b1011 "
b1011 (
#1895
0%
#1900
1%
#1901
b1100 "
b1100 (
#1905
0%
#1910
1%
#1911
b1101 "
b1101 (
#1915
0%
#1920
1%
#1921
b1110 "
b1110 (
#1925
0%
#1930
1%
#1931
b1111 "
b1111 (
#1935
0%
#1940
1%
#1941
b0 "
b0 (
1$
#1942
b1100 !
b1100 )
#1945
0%
#1950
1%
#1951
b1 "
b1 (
0$
#1955
0%
#1960
1%
#1961
b10 "
b10 (
#1965
0%
#1970
1%
#1971
b11 "
b11 (
#1975
0%
#1980
1%
#1981
b100 "
b100 (
#1985
0%
#1990
1%
#1991
b101 "
b101 (
#1995
0%
#2000
1%
#2001
b110 "
b110 (
#2005
0%
#2010
1%
#2011
b111 "
b111 (
#2015
0%
#2020
1%
#2021
b1000 "
b1000 (
#2025
0%
#2030
1%
#2031
b1001 "
b1001 (
#2035
0%
#2040
1%
#2041
b1010 "
b1010 (
#2045
0%
#2050
1%
#2051
b1011 "
b1011 (
#2055
0%
#2060
1%
#2061
b1100 "
b1100 (
#2065
0%
#2070
1%
#2071
b1101 "
b1101 (
#2075
0%
#2080
1%
#2081
b1110 "
b1110 (
#2085
0%
#2090
1%
#2091
b1111 "
b1111 (
#2095
0%
#2100
1%
#2101
b0 "
b0 (
1$
#2102
b1101 !
b1101 )
#2105
0%
#2110
1%
#2111
b1 "
b1 (
0$
#2115
0%
#2120
1%
#2121
b10 "
b10 (
#2125
0%
#2130
1%
#2131
b11 "
b11 (
#2135
0%
#2140
1%
#2141
b100 "
b100 (
#2145
0%
#2150
1%
#2151
b101 "
b101 (
#2155
0%
#2160
1%
#2161
b110 "
b110 (
#2165
0%
#2170
1%
#2171
b111 "
b111 (
#2175
0%
#2180
1%
#2181
b1000 "
b1000 (
#2185
0%
#2190
1%
#2191
b1001 "
b1001 (
#2195
0%
#2200
1%
#2201
b1010 "
b1010 (
#2205
0%
#2210
1%
#2211
b1011 "
b1011 (
#2215
0%
#2220
1%
#2221
b1100 "
b1100 (
#2225
0%
#2230
1%
#2231
b1101 "
b1101 (
#2235
0%
#2240
1%
#2241
b1110 "
b1110 (
#2245
0%
#2250
1%
#2251
b1111 "
b1111 (
#2255
0%
#2260
1%
#2261
b0 "
b0 (
1$
#2262
b1110 !
b1110 )
#2265
0%
#2270
1%
#2271
b1 "
b1 (
0$
#2275
0%
#2280
1%
#2281
b10 "
b10 (
#2285
0%
#2290
1%
#2291
b11 "
b11 (
#2295
0%
#2300
1%
#2301
b100 "
b100 (
#2305
0%
#2310
1%
#2311
b101 "
b101 (
#2315
0%
#2320
1%
#2321
b110 "
b110 (
#2325
0%
#2330
1%
#2331
b111 "
b111 (
#2335
0%
#2340
1%
#2341
b1000 "
b1000 (
#2345
0%
#2350
1%
#2351
b1001 "
b1001 (
#2355
0%
#2360
1%
#2361
b1010 "
b1010 (
#2365
0%
#2370
1%
#2371
b1011 "
b1011 (
#2375
0%
#2380
1%
#2381
b1100 "
b1100 (
#2385
0%
#2390
1%
#2391
b1101 "
b1101 (
#2395
0%
#2400
1%
#2401
b1110 "
b1110 (
#2405
0%
#2410
1%
#2411
b1111 "
b1111 (
#2415
0%
#2420
1%
#2421
b0 "
b0 (
1$
#2422
b1111 !
b1111 )
#2425
0%
#2430
1%
#2431
b1 "
b1 (
0$
#2435
0%
#2440
1%
#2441
b10 "
b10 (
#2445
0%
#2450
1%
#2451
b11 "
b11 (
#2455
0%
#2460
1%
#2461
b100 "
b100 (
#2465
0%
#2470
1%
#2471
b101 "
b101 (
#2475
0%
#2480
1%
#2481
b110 "
b110 (
#2485
0%
#2490
1%
#2491
b111 "
b111 (
#2495
0%
#2500
1%
#2501
b1000 "
b1000 (
#2505
0%
#2510
1%
#2511
b1001 "
b1001 (
#2515
0%
#2520
1%
#2521
b1010 "
b1010 (
#2525
0%
#2530
1%
#2531
b1011 "
b1011 (
#2535
0%
#2540
1%
#2541
b1100 "
b1100 (
#2545
0%
#2550
1%
#2551
b1101 "
b1101 (
#2555
0%
#2560
1%
#2561
b1110 "
b1110 (
#2565
0%
#2570
1%
#2571
b1111 "
b1111 (
#2575
0%
#2580
1%
#2581
b0 "
b0 (
1$
#2582
b0 !
b0 )
1#
#2585
0%
#2590
1%
#2591
b1 "
b1 (
0$
#2595
0%
#2600
1%
#2601
b10 "
b10 (
#2605
0%
#2610
1%
#2611
b11 "
b11 (
#2615
0%
#2620
1%
#2621
b100 "
b100 (
#2625
0%
#2630
1%
#2631
b101 "
b101 (
#2635
0%
#2640
1%
#2641
b110 "
b110 (
#2645
0%
#2650
1%
#2651
b111 "
b111 (
#2655
0%
#2660
1%
#2661
b1000 "
b1000 (
#2665
0%
#2670
1%
#2671
b1001 "
b1001 (
#2675
0%
#2680
1%
#2681
b1010 "
b1010 (
#2685
0%
#2690
1%
#2691
b1011 "
b1011 (
#2695
0%
#2700
1%
#2701
b1100 "
b1100 (
#2705
0%
#2710
1%
#2711
b1101 "
b1101 (
#2715
0%
#2720
1%
#2721
b1110 "
b1110 (
#2725
0%
#2730
1%
#2731
b1111 "
b1111 (
#2735
0%
#2740
1%
#2741
b0 "
b0 (
1$
#2742
b1 !
b1 )
0#
#2745
0%
#2750
1%
#2751
b1 "
b1 (
0$
#2755
0%
#2760
1%
#2761
b10 "
b10 (
#2765
0%
#2770
1%
#2771
b11 "
b11 (
#2775
0%
#2780
1%
#2781
b100 "
b100 (
#2785
0%
#2790
1%
#2791
b101 "
b101 (
#2795
0%
#2800
1%
#2801
b110 "
b110 (
#2805
0%
#2810
1%
#2811
b111 "
b111 (
#2815
0%
#2820
1%
#2821
b1000 "
b1000 (
#2825
0%
#2830
1%
#2831
b1001 "
b1001 (
#2835
0%
#2840
1%
#2841
b1010 "
b1010 (
#2845
0%
#2850
1%
#2851
b1011 "
b1011 (
#2855
0%
#2860
1%
#2861
b1100 "
b1100 (
#2865
0%
#2870
1%
#2871
b1101 "
b1101 (
#2875
0%
#2880
1%
#2881
b1110 "
b1110 (
#2885
0%
#2890
1%
#2891
b1111 "
b1111 (
#2895
0%
#2900
1%
#2901
b0 "
b0 (
1$
#2902
b10 !
b10 )
#2905
0%
#2910
1%
#2911
b1 "
b1 (
0$
#2915
0%
#2920
1%
#2921
b10 "
b10 (
#2925
0%
#2930
1%
#2931
b11 "
b11 (
#2935
0%
#2940
1%
#2941
b100 "
b100 (
#2945
0%
#2950
1%
#2951
b101 "
b101 (
#2955
0%
#2960
1%
#2961
b110 "
b110 (
#2965
0%
#2970
1%
#2971
b111 "
b111 (
#2975
0%
#2980
1%
#2981
b1000 "
b1000 (
#2985
0%
#2990
1%
#2991
b1001 "
b1001 (
#2995
0%
#3000
1%
#3001
b1010 "
b1010 (
#3005
0%
#3010
1%
#3011
b1011 "
b1011 (
#3015
0%
#3020
1%
#3021
b1100 "
b1100 (
#3025
0%
#3030
1%
#3031
b1101 "
b1101 (
#3035
0%
#3040
1%
#3041
b1110 "
b1110 (
#3045
0%
#3050
1%
#3051
b1111 "
b1111 (
#3055
0%
#3060
1%
#3061
b0 "
b0 (
1$
#3062
b11 !
b11 )
#3065
0%
#3070
1%
#3071
b1 "
b1 (
0$
#3075
0%
#3080
1%
#3081
b10 "
b10 (
#3085
0%
#3090
1%
#3091
b11 "
b11 (
#3095
0%
#3100
1%
#3101
b100 "
b100 (
#3105
0%
#3110
1%
#3111
b101 "
b101 (
#3115
0%
#3120
1%
#3121
b110 "
b110 (
#3125
0%
#3130
1%
#3131
b111 "
b111 (
#3135
0%
#3140
1%
#3141
b1000 "
b1000 (
#3145
0%
#3150
1%
#3151
b1001 "
b1001 (
#3155
0%
#3160
1%
#3161
b1010 "
b1010 (
#3165
0%
#3170
1%
#3171
b1011 "
b1011 (
#3175
0%
#3180
1%
#3181
b1100 "
b1100 (
#3185
0%
#3190
1%
#3191
b1101 "
b1101 (
#3195
0%
#3200
1%
#3201
b1110 "
b1110 (
#3205
0%
#3210
1%
#3211
b1111 "
b1111 (
#3215
0%
#3220
1%
#3221
b0 "
b0 (
1$
#3222
b100 !
b100 )
#3225
0%
#3230
1%
#3231
b1 "
b1 (
0$
#3235
0%
#3240
1%
#3241
b10 "
b10 (
#3245
0%
#3250
1%
#3251
b11 "
b11 (
#3255
0%
#3260
1%
#3261
b100 "
b100 (
#3265
0%
#3270
1%
#3271
b101 "
b101 (
#3275
0%
#3280
1%
#3281
b110 "
b110 (
#3285
0%
#3290
1%
#3291
b111 "
b111 (
#3295
0%
#3300
1%
#3301
b1000 "
b1000 (
#3305
0%
#3310
1%
#3311
b1001 "
b1001 (
#3315
0%
#3320
1%
#3321
b1010 "
b1010 (
#3325
0%
#3330
1%
#3331
b1011 "
b1011 (
#3335
0%
#3340
1%
#3341
b1100 "
b1100 (
#3345
0%
#3350
1%
#3351
b1101 "
b1101 (
#3355
0%
#3360
1%
#3361
b1110 "
b1110 (
#3365
0%
#3370
1%
#3371
b1111 "
b1111 (
#3375
0%
#3380
1%
#3381
b0 "
b0 (
1$
#3382
b101 !
b101 )
#3385
0%
#3390
1%
#3391
b1 "
b1 (
0$
#3395
0%
#3400
1%
#3401
b10 "
b10 (
#3405
0%
#3410
1%
#3411
b11 "
b11 (
#3415
0%
#3420
1%
#3421
b100 "
b100 (
#3425
0%
#3430
1%
#3431
b101 "
b101 (
#3435
0%
#3440
1%
#3441
b110 "
b110 (
#3445
0%
#3450
1%
#3451
b111 "
b111 (
#3455
0%
#3460
1%
#3461
b1000 "
b1000 (
#3465
0%
#3470
1%
#3471
b1001 "
b1001 (
#3475
0%
#3480
1%
#3481
b1010 "
b1010 (
#3485
0%
#3490
1%
#3491
b1011 "
b1011 (
#3495
0%
#3500
1%
#3501
b1100 "
b1100 (
#3505
0%
#3510
1%
#3511
b1101 "
b1101 (
#3515
0%
#3520
1%
#3521
b1110 "
b1110 (
#3525
0%
#3530
1%
#3531
b1111 "
b1111 (
#3535
0%
#3540
1%
#3541
b0 "
b0 (
1$
#3542
b110 !
b110 )
#3545
0%
#3550
1%
#3551
b1 "
b1 (
0$
#3555
0%
#3560
1%
#3561
b10 "
b10 (
#3565
0%
#3570
1%
#3571
b11 "
b11 (
#3575
0%
#3580
1%
#3581
b100 "
b100 (
#3585
0%
#3590
1%
#3591
b101 "
b101 (
#3595
0%
#3600
1%
#3601
b110 "
b110 (
#3605
0%
#3610
1%
#3611
b111 "
b111 (
#3615
0%
#3620
1%
#3621
b1000 "
b1000 (
#3625
0%
#3630
1%
#3631
b1001 "
b1001 (
#3635
0%
#3640
1%
#3641
b1010 "
b1010 (
#3645
0%
#3650
1%
#3651
b1011 "
b1011 (
#3655
0%
#3660
1%
#3661
b1100 "
b1100 (
#3665
0%
#3670
1%
#3671
b1101 "
b1101 (
#3675
0%
#3680
1%
#3681
b1110 "
b1110 (
#3685
0%
#3690
1%
#3691
b1111 "
b1111 (
#3695
0%
#3700
1%
#3701
b0 "
b0 (
1$
#3702
b111 !
b111 )
#3705
0%
#3710
1%
#3711
b1 "
b1 (
0$
#3715
0%
#3720
1%
#3721
b10 "
b10 (
#3725
0%
#3730
1%
#3731
b11 "
b11 (
#3735
0%
#3740
1%
#3741
b100 "
b100 (
#3745
0%
#3750
1%
#3751
b101 "
b101 (
#3755
0%
#3760
1%
#3761
b110 "
b110 (
#3765
0%
#3770
1%
#3771
b111 "
b111 (
#3775
0%
#3780
1%
#3781
b1000 "
b1000 (
#3785
0%
#3790
1%
#3791
b1001 "
b1001 (
#3795
0%
#3800
1%
#3801
b1010 "
b1010 (
#3805
0%
#3810
1%
#3811
b1011 "
b1011 (
#3815
0%
#3820
1%
#3821
b1100 "
b1100 (
#3825
0%
#3830
1%
#3831
b1101 "
b1101 (
#3835
0%
#3840
1%
#3841
b1110 "
b1110 (
#3845
0%
#3850
1%
#3851
b1111 "
b1111 (
#3855
0%
#3860
1%
#3861
b0 "
b0 (
1$
#3862
b1000 !
b1000 )
#3865
0%
#3870
1%
#3871
b1 "
b1 (
0$
#3875
0%
#3880
1%
#3881
b10 "
b10 (
#3885
0%
#3890
1%
#3891
b11 "
b11 (
#3895
0%
#3900
1%
#3901
b100 "
b100 (
#3905
0%
#3910
1%
#3911
b101 "
b101 (
#3915
0%
#3920
1%
#3921
b110 "
b110 (
#3925
0%
#3930
1%
#3931
b111 "
b111 (
#3935
0%
#3940
1%
#3941
b1000 "
b1000 (
#3945
0%
#3950
1%
#3951
b1001 "
b1001 (
#3955
0%
#3960
1%
#3961
b1010 "
b1010 (
#3965
0%
#3970
1%
#3971
b1011 "
b1011 (
#3975
0%
#3980
1%
#3981
b1100 "
b1100 (
#3985
0%
#3990
1%
#3991
b1101 "
b1101 (
#3995
0%
#4000
1%
#4001
b1110 "
b1110 (
#4005
0%
#4010
1%
#4011
b1111 "
b1111 (
#4015
0%
#4020
1%
#4021
b0 "
b0 (
1$
#4022
b1001 !
b1001 )
#4025
0%
#4030
1%
#4031
b1 "
b1 (
0$
#4035
0%
#4040
1%
#4041
b10 "
b10 (
#4045
0%
#4050
1%
#4051
b11 "
b11 (
#4055
0%
#4060
1%
#4061
b100 "
b100 (
#4065
0%
#4070
1%
#4071
b101 "
b101 (
#4075
0%
#4080
1%
#4081
b110 "
b110 (
#4085
0%
#4090
1%
#4091
b111 "
b111 (
#4095
0%
#4100
1%
#4101
b1000 "
b1000 (
#4105
0%
#4110
1%
#4111
b1001 "
b1001 (
#4115
0%
#4120
1%
#4121
b1010 "
b1010 (
#4125
0%
#4130
1%
#4131
b1011 "
b1011 (
#4135
0%
#4140
1%
#4141
b1100 "
b1100 (
#4145
0%
#4150
1%
#4151
b1101 "
b1101 (
#4155
0%
#4160
1%
#4161
b1110 "
b1110 (
#4165
0%
#4170
1%
#4171
b1111 "
b1111 (
#4175
0%
#4180
1%
#4181
b0 "
b0 (
1$
#4182
b1010 !
b1010 )
#4185
0%
#4190
1%
#4191
b1 "
b1 (
0$
#4195
0%
#4200
1%
#4201
b10 "
b10 (
#4205
0%
#4210
1%
#4211
b11 "
b11 (
#4215
0%
#4220
1%
#4221
b100 "
b100 (
#4225
0%
#4230
1%
#4231
b101 "
b101 (
#4235
0%
#4240
1%
#4241
b110 "
b110 (
#4245
0%
#4250
1%
#4251
b111 "
b111 (
#4255
0%
#4260
1%
#4261
b1000 "
b1000 (
#4265
0%
#4270
1%
#4271
b1001 "
b1001 (
#4275
0%
#4280
1%
#4281
b1010 "
b1010 (
#4285
0%
#4290
1%
#4291
b1011 "
b1011 (
#4295
0%
#4300
1%
#4301
b1100 "
b1100 (
#4305
0%
#4310
1%
#4311
b1101 "
b1101 (
#4315
0%
#4320
1%
#4321
b1110 "
b1110 (
#4325
0%
#4330
1%
#4331
b1111 "
b1111 (
#4335
0%
#4340
1%
#4341
b0 "
b0 (
1$
#4342
b1011 !
b1011 )
#4345
0%
#4350
1%
#4351
b1 "
b1 (
0$
#4355
0%
#4360
1%
#4361
b10 "
b10 (
#4365
0%
#4370
1%
#4371
b11 "
b11 (
#4375
0%
#4380
1%
#4381
b100 "
b100 (
#4385
0%
#4390
1%
#4391
b101 "
b101 (
#4395
0%
#4400
1%
#4401
b110 "
b110 (
#4405
0%
#4410
1%
#4411
b111 "
b111 (
#4415
0%
#4420
1%
#4421
b1000 "
b1000 (
#4425
0%
#4430
1%
#4431
b1001 "
b1001 (
#4435
0%
#4440
1%
#4441
b1010 "
b1010 (
#4445
0%
#4450
1%
#4451
b1011 "
b1011 (
#4455
0%
#4460
1%
#4461
b1100 "
b1100 (
#4465
0%
#4470
1%
#4471
b1101 "
b1101 (
#4475
0%
#4480
1%
#4481
b1110 "
b1110 (
#4485
0%
#4490
1%
